skill_markII_audio_receiver/__init__.py
skill_markII_audio_receiver/systemd.py
skill_markII_audio_receiver/version.py
skill_markII_audio_receiver/locale/en-us/dialog/acknowledge.dialog
skill_markII_audio_receiver/locale/en-us/dialog/disabled-service.dialog
skill_markII_audio_receiver/locale/en-us/dialog/enabled-service.dialog
skill_markII_audio_receiver/locale/en-us/dialog/generic-error.dialog
skill_markII_audio_receiver/locale/en-us/dialog/get-new-name.dialog
skill_markII_audio_receiver/locale/en-us/dialog/pairing.dialog
skill_markII_audio_receiver/locale/en-us/dialog/renamed-device.dialog
skill_markII_audio_receiver/locale/en-us/dialog/service-status.dialog
skill_markII_audio_receiver/locale/en-us/dialog/trouble-checking-service.dialog
skill_markII_audio_receiver/locale/en-us/dialog/trouble-renaming-device.dialog
skill_markII_audio_receiver/locale/en-us/dialog/try-again-later.dialog
skill_markII_audio_receiver/locale/en-us/dialog/unsure.dialog
skill_markII_audio_receiver/locale/en-us/intents/check-service-status.intent
skill_markII_audio_receiver/locale/en-us/intents/disable-airplay.intent
skill_markII_audio_receiver/locale/en-us/intents/disable-bluetooth.intent
skill_markII_audio_receiver/locale/en-us/intents/disable-kde-connect.intent
skill_markII_audio_receiver/locale/en-us/intents/disable-spotify.intent
skill_markII_audio_receiver/locale/en-us/intents/enable-airplay.intent
skill_markII_audio_receiver/locale/en-us/intents/enable-bluetooth.intent
skill_markII_audio_receiver/locale/en-us/intents/enable-kde-connect.intent
skill_markII_audio_receiver/locale/en-us/intents/enable-spotify.intent
skill_markII_audio_receiver/locale/en-us/intents/pair-bluetooth.intent
skill_markII_audio_receiver/locale/en-us/intents/pair-kde-connect.intent
skill_markII_audio_receiver/locale/en-us/intents/rename-airplay.intent
skill_markII_audio_receiver/locale/en-us/intents/rename-spotify.intent
skill_markII_audio_receiver-0.1.0.dist-info/METADATA
skill_markII_audio_receiver-0.1.0.dist-info/WHEEL
skill_markII_audio_receiver-0.1.0.dist-info/entry_points.txt
skill_markII_audio_receiver-0.1.0.dist-info/top_level.txt
skill_markII_audio_receiver-0.1.0.dist-info/RECORD
