Metadata-Version: 2.1
Name: skill-markII-audio-receiver
Version: 0.1.0
Summary: Neon.AI Mark 2 Skill for Audio Receiving - Bluetooth, Airplay, KDE Connect, Raspotify
Home-page: https://github.com/NeonGeckoCom/skill-mark2-audio-receiver
Author: Mike Gray
Author-email: mike@graywind.org
Keywords: Neon devicecontrol spotify kdeconnect airplay bluetooth mark2 audio cast
Requires-Dist: ovos-bus-client
Requires-Dist: ovos-utils
Requires-Dist: ovos-workshop
